fettuccine/__init__.py
fettuccine/git.py
fettuccine-0.1.2.dist-info/LICENSE
fettuccine-0.1.2.dist-info/METADATA
fettuccine-0.1.2.dist-info/WHEEL
fettuccine-0.1.2.dist-info/top_level.txt
fettuccine-0.1.2.dist-info/RECORD
